django_countries/__init__.py
django_countries/base.py
django_countries/conf.py
django_countries/data.py
django_countries/fields.py
django_countries/filters.py
django_countries/ioc_data.py
django_countries/makesprite.py
django_countries/models.py
django_countries/py.typed
django_countries/release.py
django_countries/serializer_fields.py
django_countries/serializers.py
django_countries/widgets.py
django_countries/graphql/__init__.py
django_countries/graphql/types.py
django_countries/locale/af/LC_MESSAGES/django.mo
django_countries/locale/af/LC_MESSAGES/django.po
django_countries/locale/ar/LC_MESSAGES/django.mo
django_countries/locale/ar/LC_MESSAGES/django.po
django_countries/locale/bg/LC_MESSAGES/django.mo
django_countries/locale/bg/LC_MESSAGES/django.po
django_countries/locale/ca/LC_MESSAGES/django.mo
django_countries/locale/ca/LC_MESSAGES/django.po
django_countries/locale/cs/LC_MESSAGES/django.mo
django_countries/locale/cs/LC_MESSAGES/django.po
django_countries/locale/da/LC_MESSAGES/django.mo
django_countries/locale/da/LC_MESSAGES/django.po
django_countries/locale/de/LC_MESSAGES/django.mo
django_countries/locale/de/LC_MESSAGES/django.po
django_countries/locale/el/LC_MESSAGES/django.mo
django_countries/locale/el/LC_MESSAGES/django.po
django_countries/locale/en@test/LC_MESSAGES/django.mo
django_countries/locale/en@test/LC_MESSAGES/django.po
django_countries/locale/eo/LC_MESSAGES/django.mo
django_countries/locale/eo/LC_MESSAGES/django.po
django_countries/locale/es/LC_MESSAGES/django.mo
django_countries/locale/es/LC_MESSAGES/django.po
django_countries/locale/et/LC_MESSAGES/django.mo
django_countries/locale/et/LC_MESSAGES/django.po
django_countries/locale/eu/LC_MESSAGES/django.mo
django_countries/locale/eu/LC_MESSAGES/django.po
django_countries/locale/eu_ES/LC_MESSAGES/django.mo
django_countries/locale/eu_ES/LC_MESSAGES/django.po
django_countries/locale/fa/LC_MESSAGES/django.mo
django_countries/locale/fa/LC_MESSAGES/django.po
django_countries_mwisslead-7.6.dev20231227150048.dist-info/LICENSE
django_countries_mwisslead-7.6.dev20231227150048.dist-info/METADATA
django_countries_mwisslead-7.6.dev20231227150048.dist-info/WHEEL
django_countries_mwisslead-7.6.dev20231227150048.dist-info/top_level.txt
django_countries_mwisslead-7.6.dev20231227150048.dist-info/RECORD
