Metadata-Version: 2.1
Name: django-countries-mwisslead
Version: 7.6.dev20231227150048
Summary: Provides a country field for Django models.
Home-page: https://github.com/SmileyChris/django-countries/
Author: Chris Beaven
Author-email: smileychris@gmail.com
License: MIT
Project-URL: Change Log, https://github.com/SmileyChris/django-countries/blob/main/CHANGES.rst
Project-URL: Source Code, https://github.com/SmileyChris/django-countries
Keywords: django,countries,flags
Classifier: Development Status :: 5 - Production/Stable
Classifier: Environment :: Web Environment
Classifier: Intended Audience :: Developers
Classifier: License :: OSI Approved :: MIT License
Classifier: Operating System :: OS Independent
Classifier: Programming Language :: Python
Classifier: Programming Language :: Python :: 3 :: Only
Classifier: Programming Language :: Python :: 3.7
Classifier: Programming Language :: Python :: 3.8
Classifier: Programming Language :: Python :: 3.9
Classifier: Programming Language :: Python :: 3.10
Classifier: Programming Language :: Python :: 3.11
Classifier: Framework :: Django
Classifier: Framework :: Django :: 3.2
Classifier: Framework :: Django :: 4.0
Classifier: Framework :: Django :: 4.1
License-File: LICENSE
Requires-Dist: asgiref
Requires-Dist: typing-extensions
Provides-Extra: dev
Requires-Dist: tox ; extra == 'dev'
Requires-Dist: black ; extra == 'dev'
Requires-Dist: django ; extra == 'dev'
Requires-Dist: pytest ; extra == 'dev'
Requires-Dist: pytest-django ; extra == 'dev'
Requires-Dist: djangorestframework ; extra == 'dev'
Requires-Dist: graphene-django ; extra == 'dev'
Provides-Extra: maintainer
Requires-Dist: transifex-client ; extra == 'maintainer'
Requires-Dist: zest.releaser[recommended] ; extra == 'maintainer'
Requires-Dist: django ; extra == 'maintainer'
Provides-Extra: pyuca
Requires-Dist: pyuca ; extra == 'pyuca'
Provides-Extra: test
Requires-Dist: pytest ; extra == 'test'
Requires-Dist: pytest-django ; extra == 'test'
Requires-Dist: pytest-cov ; extra == 'test'
Requires-Dist: djangorestframework ; extra == 'test'
Requires-Dist: graphene-django ; extra == 'test'
